pclpy_dependencies/__init__.py
pclpy_dependencies/__version__.py
pclpy_dependencies/pclpy_dependencies.py
pclpy_dependencies/bin/OpenNI2.dll
pclpy_dependencies/bin/freetype.dll
pclpy_dependencies/bin/libpng16.dll
pclpy_dependencies/bin/pcl_common_release.dll
pclpy_dependencies/bin/pcl_features_release.dll
pclpy_dependencies/bin/pcl_filters_release.dll
pclpy_dependencies/bin/pcl_io_ply_release.dll
pclpy_dependencies/bin/pcl_io_release.dll
pclpy_dependencies/bin/pcl_kdtree_release.dll
pclpy_dependencies/bin/pcl_keypoints_release.dll
pclpy_dependencies/bin/pcl_ml_release.dll
pclpy_dependencies/bin/pcl_octree_release.dll
pclpy_dependencies/bin/pcl_outofcore_release.dll
pclpy_dependencies/bin/pcl_people_release.dll
pclpy_dependencies/bin/pcl_recognition_release.dll
pclpy_dependencies/bin/pcl_registration_release.dll
pclpy_dependencies/bin/pcl_sample_consensus_release.dll
pclpy_dependencies/bin/pcl_search_release.dll
pclpy_dependencies/bin/pcl_segmentation_release.dll
pclpy_dependencies/bin/pcl_stereo_release.dll
pclpy_dependencies/bin/pcl_surface_release.dll
pclpy_dependencies/bin/pcl_tracking_release.dll
pclpy_dependencies/bin/pcl_visualization_release.dll
pclpy_dependencies/bin/tbb.dll
pclpy_dependencies/bin/vtkChartsCore-8.1.dll
pclpy_dependencies/bin/vtkCommonColor-8.1.dll
pclpy_dependencies/bin/vtkCommonComputationalGeometry-8.1.dll
pclpy_dependencies/bin/vtkCommonCore-8.1.dll
pclpy_dependencies/bin/vtkCommonDataModel-8.1.dll
pclpy_dependencies/bin/vtkCommonExecutionModel-8.1.dll
pclpy_dependencies/bin/vtkCommonMath-8.1.dll
pclpy_dependencies/bin/vtkCommonMisc-8.1.dll
pclpy_dependencies/bin/vtkCommonSystem-8.1.dll
pclpy_dependencies/bin/vtkCommonTransforms-8.1.dll
pclpy_dependencies/bin/vtkDICOMParser-8.1.dll
pclpy_dependencies/bin/vtkDomainsChemistry-8.1.dll
pclpy_dependencies/bin/vtkDomainsChemistryOpenGL2-8.1.dll
pclpy_dependencies/bin/vtkFiltersAMR-8.1.dll
pclpy_dependencies/bin/vtkFiltersCore-8.1.dll
pclpy_dependencies-0.2.1.dist-info/METADATA
pclpy_dependencies-0.2.1.dist-info/RECORD
pclpy_dependencies-0.2.1.dist-info/WHEEL
pclpy_dependencies-0.2.1.dist-info/top_level.txt
