Metadata-Version: 2.1
Name: pclpy-dependencies
Version: 0.2.1
Summary: Windows dependencies for pclpy: Python bindings for the Point Cloud Library
Home-page: https://github.com/davidcaron/pclpy_dependencies
Author: David Caron
Author-email: dcaron05@gmail.com
License: MIT license
Keywords: pclpy_dependencies
Platform: UNKNOWN
Classifier: Development Status :: 2 - Pre-Alpha
Classifier: Intended Audience :: Developers
Classifier: License :: OSI Approved :: MIT License
Classifier: Natural Language :: English
Classifier: Programming Language :: Python :: 3.6
Requires-Python: ==3.6.*
